initial_field
